modelopt_core/__init__.py
modelopt_core/torch/quantization/algorithms.cpython-310-x86_64-linux-gnu.so
modelopt_core/torch/quantization/config.cpython-310-x86_64-linux-gnu.so
modelopt_core/torch/quantization/qtensor/nvfp4_tensor.cpython-310-x86_64-linux-gnu.so
nvidia_modelopt_core-0.33.1.dist-info/METADATA
nvidia_modelopt_core-0.33.1.dist-info/WHEEL
nvidia_modelopt_core-0.33.1.dist-info/top_level.txt
nvidia_modelopt_core-0.33.1.dist-info/RECORD
nvidia_modelopt_core-0.33.1.dist-info/licenses/LICENSE
