Metadata-Version: 2.4
Name: nvidia-modelopt-core
Version: 0.33.1
Summary: Nvidia TensorRT Model Optimizer: a unified model optimization and deployment toolkit.
Home-page: https://github.com/NVIDIA/TensorRT-Model-Optimizer
Author: NVIDIA Corporation
License: Apache 2.0
Classifier: Programming Language :: Python :: 3
Classifier: Intended Audience :: Developers
Classifier: Intended Audience :: Science/Research
Classifier: Topic :: Scientific/Engineering :: Artificial Intelligence
Requires-Python: >=3.10,<3.13
License-File: LICENSE
Dynamic: author
Dynamic: classifier
Dynamic: description
Dynamic: description-content-type
Dynamic: home-page
Dynamic: license
Dynamic: license-file
Dynamic: requires-python
Dynamic: summary
